MANIFEST.in
setup.py
fpstool/__init__.py
fpstool/__main__.py
fpstool/fpstool
fpstool.egg-info/PKG-INFO
fpstool.egg-info/SOURCES.txt
fpstool.egg-info/dependency_links.txt
fpstool.egg-info/requires.txt
fpstool.egg-info/top_level.txt