Metadata-Version: 1.0
Name: fpstool
Version: 0.1.3
Summary: get FPS for android
Home-page: http://github.com/netease/unknown
Author: codeskyblue
Author-email: codeskyblue@gmail.com
License: MIT
Platform: UNKNOWN
